Workbook

Sheet Inputs
A1: Savli Cookware · first-cut DCF · inputs
A2: Ishaan Sethi, 15 December 2026 · ₹ crore · value at 31 March 2026, year-end discounting
A3: The three inputs
A4: 2025–26 revenue | C4: 186.4
A5: Revenue growth a year | C5: 0.12
A6: EBITDA margin | C6: 0.11
A7: WACC | C7: 0.13
A8: Fixed for this cut
A9: Depreciation, % of revenue | C9: 0.021
A10: Capex, % of revenue | C10: 0.026
A11: Working capital, % of the rise in revenue | C11: 0.22
A12: Tax on EBIT (tax desk’s working rate) | C12: 0.2517
A13: Terminal growth | C13: 0.05
A15: Balance sheet at 31 March 2026
A16: Bank borrowings (term loan 10.40 + cash credit 12.00) | C16: 22.4
A17: Loan from Hitesh Vasani | C17: 6
A18: Cash and bank balances, free to use | C18: 1.68
A19: Margin money under bank guarantees (not free cash) | C19: 2.4
A21: Blue figures are inputs. Fill the yellow cells, then change growth, margin or WACC: the DCF and Value sheets move with them.

Sheet DCF
A1: ₹ crore | B1: 2025–26A | C1: 2026–27E | D1: 2027–28E | E1: 2028–29E | F1: 2029–30E | G1: 2030–31E
A2: Revenue | B2: =Inputs!C4 | C2: =B2*(1+Inputs!$C$5) | D2: =C2*(1+Inputs!$C$5) | E2: =D2*(1+Inputs!$C$5) | F2: =E2*(1+Inputs!$C$5) | G2: =F2*(1+Inputs!$C$5)
A3: EBITDA | C3: =C2*Inputs!$C$6 | D3: =D2*Inputs!$C$6 | E3: =E2*Inputs!$C$6 | F3: =F2*Inputs!$C$6 | G3: =G2*Inputs!$C$6
A4: Less: depreciation | C4: =C2*Inputs!$C$9 | D4: =D2*Inputs!$C$9 | E4: =E2*Inputs!$C$9 | F4: =F2*Inputs!$C$9 | G4: =G2*Inputs!$C$9
A5: EBIT | C5: =C3-C4 | D5: =D3-D4 | E5: =E3-E4 | F5: =F3-F4 | G5: =G3-G4
A6: Less: tax on EBIT | D6: =D5*Inputs!$C$12 | E6: =E5*Inputs!$C$12 | F6: =F5*Inputs!$C$12 | G6: =G5*Inputs!$C$12
A7: NOPAT | D7: =D5-D6 | E7: =E5-E6 | F7: =F5-F6 | G7: =G5-G6
A8: Add back: depreciation | C8: =C4 | D8: =D4 | E8: =E4 | F8: =F4 | G8: =G4
A9: Less: capex | C9: =C2*Inputs!$C$10 | D9: =D2*Inputs!$C$10 | E9: =E2*Inputs!$C$10 | F9: =F2*Inputs!$C$10 | G9: =G2*Inputs!$C$10
A10: Less: increase in working capital | D10: =(D2-C2)*Inputs!$C$11 | E10: =(E2-D2)*Inputs!$C$11 | F10: =(F2-E2)*Inputs!$C$11 | G10: =(G2-F2)*Inputs!$C$11
A11: FCFF | D11: =D7+D8-D9-D10 | E11: =E7+E8-E9-E10 | F11: =F7+F8-F9-F10 | G11: =G7+G8-G9-G10
A12: Discount factor at WACC | C12: =1/(1+Inputs!$C$7)^1 | D12: =1/(1+Inputs!$C$7)^2 | E12: =1/(1+Inputs!$C$7)^3 | F12: =1/(1+Inputs!$C$7)^4 | G12: =1/(1+Inputs!$C$7)^5
A13: PV of FCFF | C13: =C11*C12 | D13: =D11*D12 | E13: =E11*E12 | F13: =F11*F12 | G13: =G11*G12
A15: Yellow cells are yours: work 2026–27 by hand. The later years show the formulas to follow.

Sheet Value
A1: ₹ crore | B1: Lower | C1: Base | D1: Higher
A2: WACC | B2: =C2-0.01 | C2: =Inputs!C7 | D2: =C2+0.01
A3: PV of FCFF, 2026–27 to 2030–31 | B3: =DCF!C11/(1+B2)^1+DCF!D11/(1+B2)^2+DCF!E11/(1+B2)^3+DCF!F11/(1+B2)^4+DCF!G11/(1+B2)^5 | C3: =SUM(DCF!C13:G13) | D3: =DCF!C11/(1+D2)^1+DCF!D11/(1+D2)^2+DCF!E11/(1+D2)^3+DCF!F11/(1+D2)^4+DCF!G11/(1+D2)^5
A4: Discount factor, end of 2030–31 | B4: =1/(1+B2)^5 | C4: =1/(1+C2)^5 | D4: =1/(1+D2)^5
A5: Terminal value, end of 2030–31
A6: PV of terminal value
A7: Enterprise value
A8: Net debt, 31 March 2026
A9: Equity value
A11: Terminal growth is Inputs!C13 in every column; Lower and Higher are one point either side of the base WACC.
A12: The PVs of FCFF are complete once your 2026–27 FCFF is in DCF!C11. Net debt and equity: Ishaan’s note says what counts.
